spark_acl_tools/__init__.py
spark_acl_tools/functions/__init__.py
spark_acl_tools/functions/generator.py
spark_acl_tools/functions/generator_acl.py
spark_acl_tools/utils/__init__.py
spark_acl_tools/utils/files/acl.xlsx
spark_acl_tools/utils/files/acl_complete.xlsx
spark_acl_tools/utils/files/ns.csv
spark_acl_tools-0.6.7.dist-info/LICENSE
spark_acl_tools-0.6.7.dist-info/METADATA
spark_acl_tools-0.6.7.dist-info/WHEEL
spark_acl_tools-0.6.7.dist-info/top_level.txt
spark_acl_tools-0.6.7.dist-info/RECORD
