Metadata-Version: 2.1
Name: spark-acl-tools
Version: 0.6.7
Summary: spark_acl_tools
Home-page: https://github.com/jonaqp/spark_acl_tools/
Author: Jonathan Quiza
Author-email: jony327@gmail.com
License: UNKNOWN
Download-URL: https://github.com/jonaqp/spark_acl_tools/archive/main.zip
Keywords: spark,datax,schema
Platform: UNKNOWN
Classifier: Development Status :: 5 - Production/Stable
Classifier: Intended Audience :: Developers
Classifier: Intended Audience :: Science/Research
Classifier: Topic :: Scientific/Engineering :: Artificial Intelligence
Classifier: License :: OSI Approved :: Apache Software License
Classifier: Programming Language :: Python :: 3.9
License-File: LICENSE
Requires-Dist: spark-dataframe-tools
Requires-Dist: openpyxl
Requires-Dist: xlsxwriter
